{
  "title": "Feather Fall",
  "source": "Player's Handbook",
  "lv": 1,
  "school": "transmutation",
  "ritual": false,
  "casting_time": [
    1,
    "reaction",
    [
      true,
      false,
      true
    ]
  ],
  "component_cost": false,
  "range": [
    60,
    0,
    "none"
  ],
  "duration": [
    1,
    "minute",
    false
  ],
  "text": "This spell can activate when you or a creature within 60 feet of you falls. Choose up to five falling creatures within range. A falling creature’s rate of descent slows to 60 feet per round until the spell ends. If the creature lands before the spell ends, it takes no falling damage and can land on its feet, and the spell ends for that creature.",
  "higher_lv": "No Higher Levels",
  "spell_lists": [
    "Artificer",
    "Bard",
    "Sorcerer",
    "Wizard"
  ],
  "proc": [
    "Instant",
    "none"
  ],
  "damage": [
    0,
    0,
    0,
    [
      ""
    ]
  ],
  "tags": [
    "Utility",
    "Movement"
  ]
}
